{
    "haskell.nix": {
        "branch": "master",
        "description": "Alternative Haskell Infrastructure for Nixpkgs",
        "homepage": "https://input-output-hk.github.io/haskell.nix",
        "owner": "input-output-hk",
        "repo": "haskell.nix",
        "rev": "804981e6892c4e14b1de8ebcf5bef8ce9962e5f1",
        "sha256": "15263sl1agi4dkyw2y3iv8nv2s83pdwfyvkixcsyfjc1379ln27j",
        "type": "tarball",
        "url": "https://github.com/input-output-hk/haskell.nix/archive/804981e6892c4e14b1de8ebcf5bef8ce9962e5f1.tar.gz",
        "url_template": "https://github.com/<owner>/<repo>/archive/<rev>.tar.gz"
    },
    "iohk-nix": {
        "branch": "master",
        "description": "nix scripts shared across projects",
        "homepage": null,
        "owner": "input-output-hk",
        "repo": "iohk-nix",
        "rev": "65d5b5eabf5252c7ece10efdc507f0a5c9b2aa8a",
        "sha256": "1b2n1c3cygrczhgffq6px42hln0344l88cf0hgq78l7m5w7lysal",
        "type": "tarball",
        "url": "https://github.com/input-output-hk/iohk-nix/archive/65d5b5eabf5252c7ece10efdc507f0a5c9b2aa8a.tar.gz",
        "url_template": "https://github.com/<owner>/<repo>/archive/<rev>.tar.gz"
    }
}
